MANIFEST.in
setup.py
ankita/__init__.py
ankita/ankita_rc.py
ankita/main.py
ankita/ui_ankita.py
ankita.egg-info/PKG-INFO
ankita.egg-info/SOURCES.txt
ankita.egg-info/dependency_links.txt
ankita.egg-info/entry_points.txt
ankita.egg-info/not-zip-safe
ankita.egg-info/top_level.txt
files/ankita.desktop
files/ankita.png