Metadata-Version: 1.1
Name: ankita
Version: 3.2.3
Summary: Well designed MS-Paint like paint program written in PyQt4
Home-page: http://github.com/ksharindam/ankita
Author: Arindam Chaudhuri
Author-email: ksharindam@gmail.com
License: GNU GPLv3
Keywords: pyqt pyqt4 paint
Platform: UNKNOWN
Classifier: Development Status :: 5 - Production/Stable
Classifier: Environment :: X11 Applications :: Qt
Classifier: License :: OSI Approved :: GNU General Public License v3 (GPLv3)
Classifier: Operating System :: POSIX :: Linux
Classifier: Programming Language :: Python :: 2.7
Classifier: Topic :: Multimedia :: Graphics
